sunlm/__init__.py
sunlm/anova.py
sunlm/data.py
sunlm/regression.py
sunlm/data/__init__.py
sunlm-0.1.3.post9.dist-info/METADATA
sunlm-0.1.3.post9.dist-info/WHEEL
sunlm-0.1.3.post9.dist-info/top_level.txt
sunlm-0.1.3.post9.dist-info/RECORD
