Metadata-Version: 2.4
Name: sunlm
Version: 0.1.3.post9
Summary: A social-science-friendly toolkit for OLS regression and SPSS-like ANOVA
Author-email: "Seonwoo (Sun) Kim" <Seonwoo.Kim@nau.edu>
License: MIT
Project-URL: Homepage, https://pypi.org/project/sunlm/
Project-URL: Documentation, https://pypi.org/project/sunlm/
Keywords: statistics,ols,anova,ancova,social science,regression,spss
Requires-Python: >=3.9
Requires-Dist: pandas>=1.3
Requires-Dist: numpy>=1.21
Requires-Dist: statsmodels>=0.13
Requires-Dist: patsy>=0.5
